setup.py
engage/__init__.py
engage/__main__.py
engage/parser.py
engage/traverse.py
engage/writer.py
engage.egg-info/PKG-INFO
engage.egg-info/SOURCES.txt
engage.egg-info/dependency_links.txt
engage.egg-info/requires.txt
engage.egg-info/top_level.txt