Metadata-Version: 1.0
Name: engage
Version: 1.0.1
Summary: Sphinx autodoc templater
Home-page: https://github.com/Zwork101/engage
Author: Nathan Zilora
Author-email: zwork101@gmail.com
License: MIT
Platform: UNKNOWN
